thermadex/__init__.py
thermadex/thermal_comfort.py
thermadex-0.0.2.dist-info/licenses/LICENSE
thermadex-0.0.2.dist-info/METADATA
thermadex-0.0.2.dist-info/WHEEL
thermadex-0.0.2.dist-info/top_level.txt
thermadex-0.0.2.dist-info/RECORD
